visualize_queue/visualize_queue.py
visualize_queue-0.0.1.2.dist-info/LICENSE
visualize_queue-0.0.1.2.dist-info/METADATA
visualize_queue-0.0.1.2.dist-info/WHEEL
visualize_queue-0.0.1.2.dist-info/top_level.txt
visualize_queue-0.0.1.2.dist-info/RECORD
