Metadata-Version: 2.1
Name: visualize-queue
Version: 0.0.1.2
Summary: visualize queue with matplotlib
Home-page: https://github.com/Leejunso0/visualize_queue
Download-URL: https://github.com/Leejunso0/visualize_queue
Author: junsoo
Classifier: Programming Language :: Python :: 3
Requires: matplotlib
License-File: LICENSE
